lincalg/__init__.py
lincalg/__main__.py
lincalg/input.py
lincalg/lincalg.py
lincalg/operations/operations.py
lincalg-0.1.1.dist-info/licenses/LICENSE
lincalg-0.1.1.dist-info/METADATA
lincalg-0.1.1.dist-info/WHEEL
lincalg-0.1.1.dist-info/entry_points.txt
lincalg-0.1.1.dist-info/top_level.txt
lincalg-0.1.1.dist-info/RECORD
