Metadata-Version: 2.4
Name: lincalg
Version: 0.1.1
Summary: A simple CLI for linear algebra calculations
Author-email: Lex Gu <lexgu314@gmail.com>
Requires-Python: >=3.8
License-File: LICENSE
Requires-Dist: sympy>=1.12
Dynamic: license-file
